Pike/get_taxonomy.py
Pike/pike.py
Pike/src/call_taxonomy.py
Pike/src/get_cluster.py
Pike/src/get_consensus.py
Pike/src/get_features.py
Pike/src/get_filtered_clusters.py
Pike/src/get_good_reads.py
Pike/src/get_merge.py
Pike/src/get_pool.py
pike_meta-0.1.12.dist-info/LICENSE
pike_meta-0.1.12.dist-info/METADATA
pike_meta-0.1.12.dist-info/WHEEL
pike_meta-0.1.12.dist-info/entry_points.txt
pike_meta-0.1.12.dist-info/top_level.txt
pike_meta-0.1.12.dist-info/RECORD
