Metadata-Version: 2.1
Name: pike-meta
Version: 0.1.12
Summary: A tool for Oxford Nanopore amplicon metagenomics
Home-page: https://github.com/DanilKrivonos/Pike
Author: D.V. Krivonos
Author-email: danil01060106@gmail.com
Project-URL: Bug Tracker, https://github.com/DanilKrivonos/Pike
Classifier: Programming Language :: Python :: 3
Classifier: License :: OSI Approved :: MIT License
Classifier: Operating System :: OS Independent
Requires-Python: >=3.9
License-File: LICENSE
Requires-Dist: numpy ==1.22.4
Requires-Dist: scikit-bio ==0.5.9
Requires-Dist: biopython ==1.83
Requires-Dist: pandas ==2.2.0
Requires-Dist: scipy ==1.10.1
Requires-Dist: scikit-learn ==1.4.1.post1
Requires-Dist: hdbscan ==0.8.33
Requires-Dist: umap-learn ==0.5.5
Requires-Dist: tensorflow ==2.10.1
Requires-Dist: medaka ==1.11.3
Requires-Dist: medaka-cpu
